huaweicloudsdksecmaster/__init__.py
huaweicloudsdksecmaster/v1/__init__.py
huaweicloudsdksecmaster/v1/secmaster_async_client.py
huaweicloudsdksecmaster/v1/secmaster_client.py
huaweicloudsdksecmaster/v1/model/__init__.py
huaweicloudsdksecmaster/v1/model/action_info.py
huaweicloudsdksecmaster/v1/model/action_instance_info.py
huaweicloudsdksecmaster/v1/model/alert.py
huaweicloudsdksecmaster/v1/model/alert_alert_type.py
huaweicloudsdksecmaster/v1/model/alert_data_source.py
huaweicloudsdksecmaster/v1/model/alert_dest_geo.py
huaweicloudsdksecmaster/v1/model/alert_detail.py
huaweicloudsdksecmaster/v1/model/alert_detail_dataclass_ref.py
huaweicloudsdksecmaster/v1/model/alert_environment.py
huaweicloudsdksecmaster/v1/model/alert_file_info.py
huaweicloudsdksecmaster/v1/model/alert_malware.py
huaweicloudsdksecmaster/v1/model/alert_network_list.py
huaweicloudsdksecmaster/v1/model/alert_process.py
huaweicloudsdksecmaster/v1/model/alert_remediation.py
huaweicloudsdksecmaster/v1/model/alert_resource_list.py
huaweicloudsdksecmaster/v1/model/alert_rule.py
huaweicloudsdksecmaster/v1/model/alert_rule_template.py
huaweicloudsdksecmaster/v1/model/alert_rule_template_metric.py
huaweicloudsdksecmaster/v1/model/alert_rule_trigger.py
huaweicloudsdksecmaster/v1/model/alert_src_geo.py
huaweicloudsdksecmaster/v1/model/alert_user_info.py
huaweicloudsdksecmaster/v1/model/alter_resource_tags_in_batches_request_body.py
huaweicloudsdksecmaster/v1/model/analysis_field.py
huaweicloudsdksecmaster/v1/model/analysis_results.py
huaweicloudsdksecmaster/v1/model/aop_instance_event_data.py
huaweicloudsdksecmaster/v1/model/aop_workflow_info.py
huaweicloudsdksecmaster/v1/model/aop_workflow_version_info.py
huaweicloudsdksecmaster/v1/model/aopworkflow_instance_detail.py
huaweicloudsdksecmaster/v1/model/aopworkflow_instance_detail_dataclass.py
huaweicloudsdksecmaster/v1/model/aopworkflow_instance_detail_playbook.py
huaweicloudsdksecmaster/v1/model/aopworkflow_instance_detail_workflow.py
huaweicloudsdksecmaster-3.1.184.dist-info/METADATA
huaweicloudsdksecmaster-3.1.184.dist-info/WHEEL
huaweicloudsdksecmaster-3.1.184.dist-info/licenses/LICENSE
huaweicloudsdksecmaster-3.1.184.dist-info/RECORD
